fracdiff/__init__.py
fracdiff/fdiff.py
fracdiff/sklearn/__init__.py
fracdiff/sklearn/fracdiff.py
fracdiff/sklearn/fracdiffstat.py
fracdiff/sklearn/stat.py
fracdiff/sklearn/tol.py
fracdiff/torch/__init__.py
fracdiff/torch/functional.py
fracdiff/torch/module.py
fracdiff_modern-1.0.0.dist-info/licenses/LICENSE
fracdiff_modern-1.0.0.dist-info/METADATA
fracdiff_modern-1.0.0.dist-info/WHEEL
fracdiff_modern-1.0.0.dist-info/top_level.txt
fracdiff_modern-1.0.0.dist-info/RECORD
