Metadata-Version: 2.4
Name: fracdiff-modern
Version: 1.0.0
Summary: Super-fast fractional differentiation.
Author-email: Shota Imaki <shota.imaki.0801@gmail.com>
Maintainer-email: Reis McMillan <reismcmillan19@gmail.com>
License-Expression: BSD-3-Clause
Project-URL: repository, https://github.com/Reis-McMillan/fracdiff
Project-URL: documentation, https://Reis-McMillan.github.io/fracdiff/
Classifier: Programming Language :: Python :: 3
Classifier: Programming Language :: Python :: 3.10
Classifier: Programming Language :: Python :: 3.11
Classifier: Programming Language :: Python :: 3.12
Classifier: Programming Language :: Python :: 3.13
Classifier: Operating System :: OS Independent
Requires-Python: >=3.10
License-File: LICENSE
Requires-Dist: numpy>=1.21.2
Requires-Dist: scipy>=1.7.0
Requires-Dist: statsmodels>=0.13.0
Provides-Extra: sklearn
Requires-Dist: scikit-learn>=1.0.0; extra == "sklearn"
Provides-Extra: torch
Requires-Dist: torch>=1.10.0; extra == "torch"
Provides-Extra: dev
Requires-Dist: pytest; extra == "dev"
Requires-Dist: pytest-cov; extra == "dev"
Requires-Dist: tox; extra == "dev"
Requires-Dist: flake8; extra == "dev"
Requires-Dist: flake8-bugbear; extra == "dev"
Requires-Dist: flake8-comprehensions; extra == "dev"
Requires-Dist: furo; extra == "dev"
Requires-Dist: sphinx; extra == "dev"
Requires-Dist: sphinx_rtd_theme; extra == "dev"
Requires-Dist: sphinx-autobuild; extra == "dev"
Requires-Dist: build; extra == "dev"
Requires-Dist: twine; extra == "dev"
Dynamic: license-file
